{
  "sites": [
    {
      "category": "Dictionaries",
      "list": [
        {
          "item": "<a href=\"http://nayiri.com\">Nayiri</a> is a compilation of more than a hundred Armenian dictionaries."
        },
        {
          "item": "<a href=\"https://hy.glosbe.com/en/hy/\">Glosbe</a> is also a great English-Armenian dictionary; it contains some newer words that are absent in Nayiri."
        }
      ]
    },
    {
      "category": "Libraries",
      "description": "For more info see <a href=\"https://en.wikipedia.org/wiki/File_sharing\">this</a>.",
      "list": [
        {
          "item": "<a href=\"https://libgen.li/\">LibGen</a> is an archive of many books and articles."
        },
        {
          "item": "<a href=\"https://z-lib.is/\">Z-Library</a> is another shadow library."
        },
        {
          "item": "<a href=\"https://www.pdfdrive.com/\">PDF Drive</a> is a shadow book archive too."
        },
        {
          "item": "<a href=\"https://arar.sci.am/dlibra\">Pan-Armenian digital library</a>."
        }
      ]
    },
    {
      "category": "Religious",
      "list": [
        {
          "item": "In <a href=\"https://www.openbible.info/topics/\">OpenBible</a> one can find out what the Bible says about the interested topic."
        },
        {
          "item": "<a href=\"https://www.1patasxan.com/\">1patasxan</a> has answers to some questions about life and God (in Armenian)."
        }
      ]
    },
    {
      "category": "Miscellaneous",
      "list": [
        {
          "item": "<a href=\"https://forebears.io/\">forebears.io</a> contains information about name and surname distribution and more."
        },
        {
          "item": "<a href=\"https://www.overleaf.com/\">Overleaf</a> is an online LaTeX editor."
        },
        {
          "item": "<a href=\"https://downdetector.com/\">Downdetector</a> shows if a website is operating or is down."
        },
        {
          "item": "<a href=\"https://www.3dtuning.com/en-US/\">3D Tuning</a> is an online car configurator."
        },
        {
          "item": "<a href=\"https://fileinfo.com\">FileInfo</a> gives info about files."
        },
        {
          "item": "<a href=\"https://wikidiff.com/\">WikiDiff</a> gives info about the difference between two words."
        }
      ]
    }
  ]
}